build_dist_package/__init__.py
build_dist_package/build_dist_package.py
build_dist_package/bin/__init__.py
build_dist_package/bin/build-dist-package.py
build_dist_package-0.1.0.data/scripts/build-dist-package
build_dist_package-0.1.0.data/scripts/build-dist-package.py
tests/__init__.py
build_dist_package-0.1.0.dist-info/LICENSE
build_dist_package-0.1.0.dist-info/METADATA
build_dist_package-0.1.0.dist-info/WHEEL
build_dist_package-0.1.0.dist-info/top_level.txt
build_dist_package-0.1.0.dist-info/RECORD
